{"cameraMode":{"drawMode":0,"name":"Shaded","section":"Shading Mode"},"sceneLighting":true,"audioPlay":false,"sceneViewState":{"m_AlwaysRefresh":false,"showFog":true,"showSkybox":true,"showFlares":true,"showImageEffects":true,"showParticleSystems":true,"showVisualEffectGraphs":true,"m_FxEnabled":true},"in2DMode":false,"pivot":{"x":442.3999938964844,"y":153.0,"z":0.0},"rotation":{"x":0.18189005553722382,"y":-0.030968891456723214,"z":0.005731424316763878,"w":0.982813835144043},"size":468.1097717285156,"orthographic":true}